awesome_streamlit/__init__.py
awesome_streamlit/core/__init__.py
awesome_streamlit/core/services/__init__.py
awesome_streamlit/core/services/other.py
awesome_streamlit/core/services/resources.py
awesome_streamlit/database/__init__.py
awesome_streamlit/database/apps_in_gallery.py
awesome_streamlit/database/authors.py
awesome_streamlit/database/resources.py
awesome_streamlit/database/settings.py
awesome_streamlit/database/tags.py
awesome_streamlit/experiments/__init__.py
awesome_streamlit/experiments/hello_world.py
awesome_streamlit/shared/__init__.py
awesome_streamlit/shared/components.py
awesome_streamlit/shared/models.py
awesome_streamlit/testing/__init__.py
awesome_streamlit/testing/components.py
awesome_streamlit/testing/models.py
awesome_streamlit/testing/test_runner_app.py
awesome_streamlit/testing/utils.py
awesome_streamlit/testing/services/__init__.py
awesome_streamlit/testing/services/test_item.py
awesome_streamlit/testing/services/test_items_dataframe.py
awesome_streamlit-20200728.1.dist-info/METADATA
awesome_streamlit-20200728.1.dist-info/WHEEL
awesome_streamlit-20200728.1.dist-info/top_level.txt
awesome_streamlit-20200728.1.dist-info/RECORD
