Metadata-Version: 2.1
Name: awesome-streamlit
Version: 20200728.1
Summary: This package supports the Awesome Streamlit Project and
Home-page: https://github.com/marcskovmadsen/awesome-streamlit
Author: Marc Skov Madsen
Author-email: marc.skov.madsen@gmail.com
License: MIT
Platform: UNKNOWN
Requires-Python: >= 3.7
